preserve_podcasts/__init__.py
preserve_podcasts/__main__.py
preserve_podcasts/exception.py
preserve_podcasts/pod_sessiosn.py
preserve_podcasts/podcast.py
preserve_podcasts/preservePodcasts.py
preserve_podcasts/uploadPodcasts.py
preserve_podcasts/utils/__init__.py
preserve_podcasts/utils/file.py
preserve_podcasts/utils/fileLock.py
preserve_podcasts/utils/requests_patch.py
preserve_podcasts/utils/response.py
preserve_podcasts/utils/type_check.py
preserve_podcasts/utils/util.py
preserve_podcasts/version.py
preservethosepod-1.0.12.dist-info/METADATA
preservethosepod-1.0.12.dist-info/WHEEL
preservethosepod-1.0.12.dist-info/entry_points.txt
preservethosepod-1.0.12.dist-info/RECORD
