Metadata-Version: 2.1
Name: PreserveThosePod
Version: 1.0.12
Summary: Preserve those podcasts!
License: WTFPL
Author: yzqzss
Author-email: yzqzss@yandex.com
Requires-Python: >=3.8,<4.0
Classifier: License :: Other/Proprietary License
Classifier: Programming Language :: Python :: 3
Classifier: Programming Language :: Python :: 3.8
Classifier: Programming Language :: Python :: 3.9
Classifier: Programming Language :: Python :: 3.10
Classifier: Programming Language :: Python :: 3.11
Classifier: Programming Language :: Python :: 3.12
Requires-Dist: feedparser (>=6.0.10,<7.0.0)
Requires-Dist: internetarchive (>=3.5.0,<4.0.0)
Requires-Dist: pyrfc6266 (>=1.0.2,<2.0.0)
Requires-Dist: requests (>=2.28.2,<3.0.0)
Requires-Dist: rich (>=13.3.3,<14.0.0)
Project-URL: respository, https://github.com/saveweb/preserve-those-podcasts
